todo/__init__.py
todo/cli_parser.py
todo/core.py
todo/data_access.py
todo/init_db.py
todo/rainbow.py
todo/text_wrap.py
todo/todo.py
todo/types.py
todo/utils.py
todo/bash_completion/__init__.py
todo/bash_completion/installation.py
todo/bash_completion/toduh.sh
todocli-5.0.0.dist-info/METADATA
todocli-5.0.0.dist-info/WHEEL
todocli-5.0.0.dist-info/entry_points.txt
todocli-5.0.0.dist-info/top_level.txt
todocli-5.0.0.dist-info/RECORD
