Metadata-Version: 2.1
Name: todocli
Version: 5.0.0
Summary: A command line todo list manager
Home-page: https://github.com/foobuzz/todo
Author: foobuzz
Author-email: foobuzz@fastmail.com
License: MIT
Keywords: command line todo list
Platform: UNKNOWN
Requires-Python: >=3.8
Requires-Dist: setuptools (==65.5.1)
Provides-Extra: tests
Requires-Dist: pyfakefs (==4.5.5) ; extra == 'tests'
Requires-Dist: freezegun (==1.2.2) ; extra == 'tests'
